MANIFEST.in
README.rst
setup.cfg
setup.py
registration/__init__.py
registration/bootstrap.py
registration/controllers/__init__.py
registration/controllers/root.py
registration/i18n/registration.pot
registration/i18n/en/LC_MESSAGES/registration.po
registration/i18n/it/LC_MESSAGES/registration.mo
registration/i18n/it/LC_MESSAGES/registration.po
registration/lib/__init__.py
registration/lib/forms.py
registration/lib/validators.py
registration/migration/env.py
registration/migration/script.py.mako
registration/migration/versions/empty.txt
registration/migration/versions/f40c840032a4_add_extras_to_sqlalchemy.py
registration/model/__init__.py
registration/model/dal_interface.py
registration/model/ming_models.py
registration/model/sqla_models.py
registration/public/__init__.py
registration/public/css/style.css
registration/templates/__init__.py
registration/templates/admin.html
registration/templates/admin.xhtml
registration/templates/complete.html
registration/templates/complete.xhtml
registration/templates/register.html
registration/templates/register.xhtml
tests/__init__.py
tests/base.py
tests/test_controller.py
tests/test_controller_auth.py
tests/controllers/__init__.py
tests/controllers/root.py
tests/templates/__init__.py
tgapp_registration.egg-info/PKG-INFO
tgapp_registration.egg-info/SOURCES.txt
tgapp_registration.egg-info/dependency_links.txt
tgapp_registration.egg-info/entry_points.txt
tgapp_registration.egg-info/not-zip-safe
tgapp_registration.egg-info/requires.txt
tgapp_registration.egg-info/top_level.txt