Metadata-Version: 2.1
Name: tgapp-registration
Version: 0.9.6
Summary: Pluggable registration application for TurboGears2 with hooks for fine customization
Home-page: https://github.com/axant/tgapp-registration
Author: Alessandro Molina
Author-email: alessandro.molina@axant.it
License: UNKNOWN
Keywords: turbogears2.application
Platform: UNKNOWN
Provides-Extra: testing
